quiffen-4.0.1.dist-info/METADATA
quiffen-4.0.1.dist-info/WHEEL
quiffen-4.0.1.dist-info/entry_points.txt
quiffen-4.0.1.dist-info/licenses/LICENSE
quiffen/__init__.py
quiffen/core/__init__.py
quiffen/core/account.py
quiffen/core/base.py
quiffen/core/category.py
quiffen/core/class_type.py
quiffen/core/investment.py
quiffen/core/qif.py
quiffen/core/security.py
quiffen/core/split.py
quiffen/core/transaction.py
quiffen/utils.py
quiffen-4.0.1.dist-info/RECORD
