Metadata-Version: 2.1
Name: quiffen
Version: 4.0.1
Summary: Quiffen
Keywords: qif,finance,data processing
Author-Email: Isaac Harris-Holt <isaac@harris-holt.com>
License: MIT
Classifier: Development Status :: 5 - Production/Stable
Classifier: Intended Audience :: Developers
Classifier: Programming Language :: Python :: 3
Classifier: Operating System :: MacOS :: MacOS X
Classifier: Operating System :: Microsoft :: Windows
Project-URL: homepage, https://github.com/isaacharrisholt/quiffen
Project-URL: repository, https://github.com/isaacharrisholt/quiffen
Project-URL: documentation, https://quiffen.readthedocs.io/en/latest/
Requires-Python: <3.14,>=3.9
Requires-Dist: pydantic<3.0.0,>=2.0.0
Requires-Dist: python-dateutil<3.0.0,>=2.8.2
Provides-Extra: pandas
Requires-Dist: numpy>=1.20; python_version < "3.13" and extra == "pandas"
Requires-Dist: pandas<3.0.0,>2.2.0; python_version < "3.13" and extra == "pandas"
Requires-Dist: numpy>=2.3.1; python_version >= "3.13" and extra == "pandas"
Requires-Dist: pandas>=2.3.0; python_version >= "3.13" and extra == "pandas"
